innotescus/__init__.py
innotescus/auth.py
innotescus/cli.py
innotescus/config.ini
innotescus/datatypes.py
innotescus/exceptions.py
innotescus/helpers.py
innotescus/innotescus.py
innotescus/interceptor.py
innotescus/_grpc/ApiCommon_pb2.py
innotescus/_grpc/ApiCommon_pb2_grpc.py
innotescus/_grpc/ApiService_pb2.py
innotescus/_grpc/ApiService_pb2_grpc.py
innotescus/_grpc/Constants_pb2.py
innotescus/_grpc/Constants_pb2_grpc.py
innotescus/_grpc/__init__.py
innotescus/services/__init__.py
innotescus/services/annotation.py
innotescus/services/base.py
innotescus/services/membership.py
innotescus/services/task_review.py
innotescus-1.0.0.dist-info/METADATA
innotescus-1.0.0.dist-info/WHEEL
innotescus-1.0.0.dist-info/entry_points.txt
innotescus-1.0.0.dist-info/top_level.txt
innotescus-1.0.0.dist-info/RECORD
