Metadata-Version: 2.1
Name: innotescus
Version: 1.0.0
Summary: Client for the Innotescus Platform
Home-page: https://innotescus.io
Author: Innotescus, LLC
Author-email: support@innotescus.io
License: UNKNOWN
Platform: UNKNOWN
Classifier: Programming Language :: Python :: 3
Classifier: License :: OSI Approved :: MIT License
Classifier: Operating System :: OS Independent
Requires-Python: >=3.7
Requires-Dist: Authlib (==0.15.5)
Requires-Dist: grpcio (==1.43.0)
Requires-Dist: pyOpenSSL (==21.0.0)
Requires-Dist: grpc-interceptor (==0.13.0)
Requires-Dist: google-api-python-client
